mcutools
