Metadata-Version: 1.0
Name: mcutool
Version: 1.0.8
Summary: a arm mcu debug tool
Home-page: https://blog.xieweiming.cn
Author: xwm
Author-email: xwmdev@163.com
License: BSD License
Platform: UNKNOWN
